llama_index/retrievers/mongodb_atlas_bm25_retriever/__init__.py
llama_index/retrievers/mongodb_atlas_bm25_retriever/base.py
llama_index_retrievers_mongodb_atlas_bm25_retriever-0.4.1.dist-info/METADATA
llama_index_retrievers_mongodb_atlas_bm25_retriever-0.4.1.dist-info/WHEEL
llama_index_retrievers_mongodb_atlas_bm25_retriever-0.4.1.dist-info/licenses/LICENSE
llama_index_retrievers_mongodb_atlas_bm25_retriever-0.4.1.dist-info/RECORD
