Metadata-Version: 2.4
Name: llama-index-retrievers-mongodb-atlas-bm25-retriever
Version: 0.4.1
Summary: llama-index retrievers mongodb-atlas-bm25-retriever integration
Author-email: Your Name <you@example.com>
License-Expression: MIT
License-File: LICENSE
Requires-Python: <4.0,>=3.9
Requires-Dist: llama-index-core<0.15,>=0.13.0
Requires-Dist: pymongo<5,>=4.6.1
